nattrs/__init__.py
nattrs/deleter.py
nattrs/getter.py
nattrs/has_checker.py
nattrs/mutator.py
nattrs/populate.py
nattrs/setter.py
nattrs/updater.py
nattrs/utils.py
nattrs-0.2.3.dist-info/LICENSE
nattrs-0.2.3.dist-info/METADATA
nattrs-0.2.3.dist-info/WHEEL
nattrs-0.2.3.dist-info/RECORD
