Metadata-Version: 2.3
Name: nattrs
Version: 0.2.3
Summary: Nested attribute getter/setter that works with dictionaries and objects interchangeably.
License: MIT
Keywords: attributes,dictionaries,class,recursive,get,set,inplace
Author: Ludvig
Author-email: <mail@ludvigolsen.dk>
Requires-Python: >=3.8,<4.0
Classifier: License :: OSI Approved :: MIT License
Classifier: Programming Language :: Python :: 3
Classifier: Programming Language :: Python :: 3.8
Classifier: Programming Language :: Python :: 3.9
Classifier: Programming Language :: Python :: 3.10
Classifier: Programming Language :: Python :: 3.11
Classifier: Programming Language :: Python :: 3.12
Classifier: Programming Language :: Python :: 3.13
Requires-Dist: zipp (>=3.19.1,<4.0.0)
Project-URL: Changelog, https://github.com/ludvigolsen/nattrs/blob/main/CHANGELOG.md
Project-URL: Issues, https://github.com/ludvigolsen/nattrs/issues
Project-URL: Repository, https://github.com/ludvigolsen/nattrs
